fujin_secrets_doppler/__init__.py
fujin_secrets_doppler/py.typed
fujin_secrets_doppler-0.20.4.dist-info/WHEEL
fujin_secrets_doppler-0.20.4.dist-info/entry_points.txt
fujin_secrets_doppler-0.20.4.dist-info/METADATA
fujin_secrets_doppler-0.20.4.dist-info/RECORD
