Metadata-Version: 2.3
Name: fujin-secrets-doppler
Version: 0.20.4
Summary: Doppler secret adapter for Fujin
Author: Tobi
Author-email: Tobi <tobidegnon@proton.me>
Classifier: Programming Language :: Python :: 3 :: Only
Classifier: Programming Language :: Python :: 3.10
Classifier: Programming Language :: Python :: 3.11
Classifier: Programming Language :: Python :: 3.12
Classifier: Programming Language :: Python :: 3.13
Classifier: Programming Language :: Python :: 3.14
Requires-Dist: fujin-cli>=0.20.4
Requires-Dist: python-dotenv>=1.0.1
Requires-Python: >=3.10
Project-URL: Homepage, https://github.com/Tobi-De/fujin
Project-URL: Issues, https://github.com/Tobi-De/fujin/issues
Project-URL: Source, https://github.com/Tobi-De/fujin
